{
  "sections": {
    "166318458702f43cde": {
      "type": "hero-banner",
      "blocks": {
        "166318458772279baf-0": {
          "type": "heading",
          "settings": {
            "heading": "Image banner",
            "heading_size": "h1"
          }
        },
        "166318458772279baf-1": {
          "type": "text",
          "settings": {
            "text": "Give customers details about the banner image(s) or content on the template.",
            "text_style": "caption-with-letter-spacing"
          }
        },
        "166318458772279baf-2": {
          "type": "buttons",
          "settings": {
            "button_label_1": "Button label",
            "button_link_1": "",
            "button_style_secondary_1": false,
            "button_label_2": "Button label",
            "button_link_2": "",
            "button_style_secondary_2": false
          }
        }
      },
      "block_order": [
        "166318458772279baf-0",
        "166318458772279baf-1",
        "166318458772279baf-2"
      ],
      "settings": {
        "image": "shopify:\/\/shop_images\/The_Cats_Closer.png",
        "image_overlay_opacity": 70,
        "menu": "main-menu"
      }
    }
  },
  "order": [
    "166318458702f43cde"
  ]
}
